scikit_tab_trans/scikit_tab_tranformer.py
scikit_tabtrans-0.2.dist-info/LICENSE.md
scikit_tabtrans-0.2.dist-info/WHEEL
scikit_tabtrans-0.2.dist-info/METADATA
scikit_tabtrans-0.2.dist-info/RECORD
